cvforge/__init__.py
cvforge/ats_checker.py
cvforge/cli.py
cvforge/templates/ats-friendly-resume/example.yaml
cvforge/templates/ats-friendly-resume/main.typ
cvforge/templates/ats-friendly-resume/template.typ
cvforge-1.1.1.dist-info/METADATA
cvforge-1.1.1.dist-info/WHEEL
cvforge-1.1.1.dist-info/entry_points.txt
cvforge-1.1.1.dist-info/licenses/LICENSE
cvforge-1.1.1.dist-info/RECORD
