Metadata-Version: 2.4
Name: cvforge
Version: 1.1.1
Summary: ATS-friendly CV/Resume builder using YAML and Typst
Project-URL: Homepage, https://github.com/SoAp9035/cvforge
Project-URL: Repository, https://github.com/SoAp9035/cvforge
Project-URL: Issues, https://github.com/SoAp9035/cvforge/issues
Author-email: Ahmet Burhan Kayalı <ahmetburhan1703@gmail.com>
License: MIT
License-File: LICENSE
Keywords: ats,cv,pdf,resume,typst
Classifier: Development Status :: 4 - Beta
Classifier: Environment :: Console
Classifier: Intended Audience :: End Users/Desktop
Classifier: License :: OSI Approved :: MIT License
Classifier: Operating System :: OS Independent
Classifier: Programming Language :: Python :: 3
Classifier: Programming Language :: Python :: 3.10
Classifier: Programming Language :: Python :: 3.11
Classifier: Programming Language :: Python :: 3.12
Classifier: Programming Language :: Python :: 3.13
Classifier: Programming Language :: Python :: 3.14
Classifier: Topic :: Office/Business
Classifier: Topic :: Text Processing :: Markup
Requires-Python: >=3.10
Requires-Dist: pypdf>=4.0
Requires-Dist: pyyaml>=6.0
